MANIFEST.in
README.txt
setup.cfg
setup.py
docs/HISTORY.txt
src/plone/__init__.py
src/plone.z3ctable.egg-info/PKG-INFO
src/plone.z3ctable.egg-info/SOURCES.txt
src/plone.z3ctable.egg-info/dependency_links.txt
src/plone.z3ctable.egg-info/entry_points.txt
src/plone.z3ctable.egg-info/namespace_packages.txt
src/plone.z3ctable.egg-info/not-zip-safe
src/plone.z3ctable.egg-info/requires.txt
src/plone.z3ctable.egg-info/top_level.txt
src/plone/z3ctable/__init__.py
src/plone/z3ctable/batch.py
src/plone/z3ctable/configure.zcml
src/plone/z3ctable/tests/__init__.py
src/plone/z3ctable/tests/provider.txt
src/plone/z3ctable/tests/test_doctests.py