Metadata-Version: 1.1
Name: plone.z3ctable
Version: 0.2
Summary: z3c.table support for Plone
Home-page: https://github.com/affinitic/plone.z3ctable
Author: Godefroid Chapelle
Author-email: gotcha@bubblenet.be
License: GPL
Platform: UNKNOWN
Classifier: Programming Language :: Python
Classifier: Topic :: Software Development :: Libraries :: Python Modules
